iog_randomizer/cli/__init__.py
iog_randomizer/cli/__main__.py
iog_randomizer/gui/__init__.py
iog_randomizer/gui/gui.py
iog_randomizer/randomizer/ATlMpMuSEWaterHighSub_Tilemap1_comp.bin
iog_randomizer/randomizer/ATlMpMuSWWaterHighSub_Tilemap1_comp.bin
iog_randomizer/randomizer/ATlMpSpecInvBg_comp.bin
iog_randomizer/randomizer/ATlMpWorldMap_Tilemap1_comp.bin
iog_randomizer/randomizer/ConfigValueArray.asr
iog_randomizer/randomizer/Tilemap6D.bin
iog_randomizer/randomizer/TilemapMuPassage.bin
iog_randomizer/randomizer/__init__.py
iog_randomizer/randomizer/apocalypse_gaia_1.asr
iog_randomizer/randomizer/apocalypse_gaia_2.asr
iog_randomizer/randomizer/asar-x64.dll
iog_randomizer/randomizer/asar-x64.so
iog_randomizer/randomizer/asar-x86.dll
iog_randomizer/randomizer/asar.py
iog_randomizer/randomizer/classes.py
iog_randomizer/randomizer/errors.py
iog_randomizer/randomizer/iogr.asr
iog_randomizer/randomizer/iogr_81_exit_table.asr
iog_randomizer/randomizer/iogr_8C_actor_table.asr
iog_randomizer/randomizer/iogr_8D_asset_table.asr
iog_randomizer/randomizer/iogr_asset_ledger.asr
iog_randomizer/randomizer/iogr_code_overflow.asr
iog_randomizer/randomizer/iogr_dialogue_overflow.asr
iog_randomizer/randomizer/iogr_exit_ledger.asr
iog_randomizer/randomizer/iogr_fluteless_melody_anim.bin
iog_randomizer/randomizer/iogr_misc_defines.asr
iog_randomizer/randomizer/iogr_monster_defaults.asr
iog_randomizer/randomizer/iogr_rom.py
iog_randomizer/randomizer/patch.py
iog_randomizer/randomizer/quintet_comp.py
iog_randomizer/randomizer/quintet_text.py
iog_randomizer/randomizer/table_dialogue.txt
iog_randomizer/randomizer/table_invtext.txt
iog_randomizer/randomizer/__pycache__/asar.cpython-312.pyc
iog_randomizer/randomizer/bin/__init__.py
iog_randomizer/randomizer/bin/plugins/sprites/bagu/1a8000.bin
iog_randomizer/randomizer/bin/plugins/sprites/bagu/1b8000.bin
iog_randomizer/randomizer/bin/plugins/sprites/freet/1a820a.bin
iog_randomizer/randomizer/bin/plugins/sprites/invisible/1a8000.bin
iog_randomizer-5.1.5.3.dist-info/licenses/LICENSE
iog_randomizer-5.1.5.3.dist-info/METADATA
iog_randomizer-5.1.5.3.dist-info/WHEEL
iog_randomizer-5.1.5.3.dist-info/entry_points.txt
iog_randomizer-5.1.5.3.dist-info/top_level.txt
iog_randomizer-5.1.5.3.dist-info/RECORD
