Metadata-Version: 2.4
Name: iog-randomizer
Version: 5.1.5.3
Summary: The Illusion of Gaia Randomizer
Author: dontbagume, bryon_w, raeven0
Project-URL: Homepage, https://iogr.app/
Project-URL: Source, https://github.com/dontbagume/iogr
License-File: LICENSE
Requires-Dist: ips.py
Requires-Dist: bsdiff4
Requires-Dist: bitstring
Dynamic: license-file
